gojira/__init__.py
gojira/auth/__init__.py
gojira/auth/middleware.py
gojira/auth/models.py
gojira/constants.py
gojira/dependencies.py
gojira/exceptions.py
gojira/filters/__init__.py
gojira/filters/backends.py
gojira/filters/filters.py
gojira/filters/filterset.py
gojira/generics/__init__.py
gojira/generics/exceptions.py
gojira/generics/meta.py
gojira/generics/mixins.py
gojira/generics/models.py
gojira/generics/routes.py
gojira/generics/serializers.py
gojira/messages.py
gojira/permissions/__init__.py
gojira/permissions/base.py
gojira-0.1.2.dist-info/WHEEL
gojira-0.1.2.dist-info/METADATA
gojira-0.1.2.dist-info/RECORD
